<?xml version="1.0" encoding="UTF-8" standalone="yes"?>
<addon id="plugin.video.16bars"
       name="16bars"
       version="0.0.2"
       provider-name="r0tt">
  <requires>
    <import addon="xbmc.python" version="2.19.0"/>
  </requires>
  <extension point="xbmc.python.pluginsource"
            library="default.py">
        <provides>video</provides>
  </extension>
  <extension point="xbmc.addon.metadata">
    <summary lang="en">Watch HipHop/RapVideos</summary>
    <language>de, en</language>
    <description lang="en">Watch HipHop/RapVideos from 16bars.de; required addons: youtube, dailymotion, vimeo, myvideo</description>
    <license>GNU GENERAL PUBLIC LICENSE. Version 2, June 1991</license>
    <platform>all</platform>
    <forum></forum>
    <website>https://github.com/r0tt0r/plugin.video.16bars</website>
    <email></email>
    <source>https://github.com/r0tt0r/plugin.video.16bars</source>
  </extension>
</addon>
